COPYING
MANIFEST.in
README.md
requirements.txt
setup.py
doc/build/html/.buildinfo
doc/build/html/genindex.html
doc/build/html/index.html
doc/build/html/objects.inv
doc/build/html/search.html
doc/build/html/searchindex.js
doc/build/html/_downloads/09498372fd324e28d4d30e2308dd44d8/synthetic_data.tar.gz
doc/build/html/_downloads/291def790b2547a0f7c9b65baa8119a6/run_TA.ipynb
doc/build/html/_downloads/7575b58f099a8cf4841d9ee96b7d1e27/Fluo-N3DH-CE.tar.gz
doc/build/html/_downloads/83e9a8f742a76ae9df7ee9340bb28985/run_TA.ipynb
doc/build/html/_downloads/b6d7999a6f9823a56c2d347795e3e9d6/synthetic_data.tar.gz
doc/build/html/_downloads/dc3fbab8c634583281ec7a7443a3fe0c/Fluo-N3DH-CE.tar.gz
doc/build/html/_downloads/e35768bda47eae7db8ef1b20b2a4e16f/load_tracking.py
doc/build/html/_downloads/f055c343f55d046bef0a67c2182fc8cf/load_tracking.py
doc/build/html/_images/filter_subsets-1.png
doc/build/html/_images/filter_subsets-2.png
doc/build/html/_images/galaxy_help.jpeg
doc/build/html/_images/loading_data.png
doc/build/html/_images/map_section.png
doc/build/html/_images/ploting_parameters.png
doc/build/html/_images/setting_metadata.png
doc/build/html/_images/subset_naming.png
doc/build/html/_images/trajectory_section.png
doc/build/html/_sources/index.rst.txt
doc/build/html/_sources/developer_guide/index.rst.txt
doc/build/html/_sources/user_guide/index.rst.txt
doc/build/html/_sources/user_guide/installation.rst.txt
doc/build/html/_sources/user_guide/quickstart.rst.txt
doc/build/html/_static/_sphinx_javascript_frameworks_compat.js
doc/build/html/_static/basic.css
doc/build/html/_static/doctools.js
doc/build/html/_static/documentation_options.js
doc/build/html/_static/file.png
doc/build/html/_static/generate_synthetic_data.py
doc/build/html/_static/jquery-3.5.1.js
doc/build/html/_static/jquery-3.6.0.js
doc/build/html/_static/jquery.js
doc/build/html/_static/language_data.js
doc/build/html/_static/minus.png
doc/build/html/_static/plus.png
doc/build/html/_static/pygments.css
track_analyzer.egg-info/PKG-INFO
track_analyzer.egg-info/SOURCES.txt
track_analyzer.egg-info/dependency_links.txt
track_analyzer.egg-info/entry_points.txt
track_analyzer.egg-info/requires.txt
track_analyzer.egg-info/top_level.txt
