Metadata-Version: 2.1
Name: track_analyzer
Version: 0.5
Summary: Track Analyzer: quantification and visualization of tracking data
Home-page: https://gitlab.pasteur.fr/track-analyzer/track-analyzer
Download-URL: https://pypi.org/project/track-analyzer/
Author: Arthur Michaut
Author-email: arthur.michaut@gmail.com
License: GPLv3
Classifier: Development Status :: 5 - Production/Stable
Classifier: Environment :: Console
Classifier: Operating System :: POSIX
Classifier: Operating System :: Microsoft :: Windows
Classifier: Programming Language :: Python :: 3
Classifier: Programming Language :: Python :: 3.6
Classifier: Programming Language :: Python :: 3.7
Classifier: Programming Language :: Python :: 3.8
Classifier: Intended Audience :: Science/Research
Classifier: Topic :: Scientific/Engineering :: Bio-Informatics
Requires-Python: >=3.6
License-File: COPYING
Requires-Dist: pandas
Requires-Dist: matplotlib
Requires-Dist: scikit-image
Requires-Dist: scipy
Requires-Dist: seaborn>=0.12
Requires-Dist: lmfit
Requires-Dist: tifffile
Requires-Dist: jupyter
Requires-Dist: ipyfilechooser
Requires-Dist: ipywidgets
Requires-Dist: tqdm
Requires-Dist: shapely
